chrondb/__init__.py
chrondb/_ffi.py
chrondb/client.py
chrondb/lib/libchrondb.so
chrondb-0.0.0.dev15.dist-info/METADATA
chrondb-0.0.0.dev15.dist-info/WHEEL
chrondb-0.0.0.dev15.dist-info/top_level.txt
chrondb-0.0.0.dev15.dist-info/RECORD
