Metadata-Version: 2.4
Name: chrondb
Version: 0.0.0.dev15
Summary: Python bindings for ChronDB - a time-traveling key/value database
License: AGPL-3.0
Project-URL: Repository, https://github.com/avelino/chrondb
Requires-Python: >=3.8
